prune_ebs_snapshots.py
prune_ebs_snapshots-0.5.0.dist-info/DESCRIPTION.rst
prune_ebs_snapshots-0.5.0.dist-info/LICENSE.txt
prune_ebs_snapshots-0.5.0.dist-info/METADATA
prune_ebs_snapshots-0.5.0.dist-info/RECORD
prune_ebs_snapshots-0.5.0.dist-info/WHEEL
prune_ebs_snapshots-0.5.0.dist-info/entry_points.txt
prune_ebs_snapshots-0.5.0.dist-info/metadata.json
prune_ebs_snapshots-0.5.0.dist-info/top_level.txt
