Metadata-Version: 2.0
Name: prune-ebs-snapshots
Version: 0.5.0
Summary: Prune EBS snapshots based on a simple backup retention policy
Home-page: https://github.com/ammojamo/prune-ebs-snapshots
Author: James Watmuff
Author-email: james.watmuff@gmail.com
License: Apache2
Platform: UNKNOWN
Classifier: Development Status :: 4 - Beta
Classifier: Intended Audience :: System Administrators
Classifier: License :: OSI Approved :: Apache Software License
Classifier: Programming Language :: Python :: 2
Classifier: Programming Language :: Python :: 3
Requires-Dist: boto3 (>=1.4.4)
Requires-Dist: python-dateutil (>=2.6.0)
Requires-Dist: pytz (>=2017.2)
